cli/__init__.py
cli/last_run.py
cli/ppg.py
outputs/__init__.py
outputs/events.py
outputs/json_handler.py
outputs/osx_clipboard.py
outputs/output_handler.py
outputs/single_file_handler.py
prompts/__init__.py
prompts/file_processor.py
prompts/generator.py
prompts/options.py
prompts/sensitive_masker.py
utils/__init__.py
utils/envrc.py
utils/file_walker.py
utils/ignore_handler.py
utils/language_mapping.py
project_prompt_generator-0.1.7.dist-info/LICENSE
project_prompt_generator-0.1.7.dist-info/METADATA
project_prompt_generator-0.1.7.dist-info/WHEEL
project_prompt_generator-0.1.7.dist-info/entry_points.txt
project_prompt_generator-0.1.7.dist-info/top_level.txt
project_prompt_generator-0.1.7.dist-info/RECORD
